qt4_doc_mcp_server/__init__.py
qt4_doc_mcp_server/cache.py
qt4_doc_mcp_server/cli.py
qt4_doc_mcp_server/config.py
qt4_doc_mcp_server/convert.py
qt4_doc_mcp_server/doc_service.py
qt4_doc_mcp_server/errors.py
qt4_doc_mcp_server/fetcher.py
qt4_doc_mcp_server/main.py
qt4_doc_mcp_server/search.py
qt4_doc_mcp_server/server.py
qt4_doc_mcp_server/tools.py
qt4_doc_mcp_server-0.4.0.dist-info/METADATA
qt4_doc_mcp_server-0.4.0.dist-info/WHEEL
qt4_doc_mcp_server-0.4.0.dist-info/entry_points.txt
qt4_doc_mcp_server-0.4.0.dist-info/licenses/LICENSE
qt4_doc_mcp_server-0.4.0.dist-info/RECORD
