Metadata-Version: 2.4
Name: qt4-doc-mcp-server
Version: 0.4.0
Summary: Offline MCP Server for Qt 4.8.4 documentation
Project-URL: Homepage, https://github.com/jztan/qt4-doc-mcp-server
Project-URL: Repository, https://github.com/jztan/qt4-doc-mcp-server.git
Project-URL: Issues, https://github.com/jztan/qt4-doc-mcp-server/issues
Project-URL: Changelog, https://github.com/jztan/qt4-doc-mcp-server/blob/master/CHANGELOG.md
Author-email: Kevin Tan <jingzheng.tan@gmail.com>
Maintainer-email: Kevin Tan <jingzheng.tan@gmail.com>
License: MIT License
License-File: LICENSE
Keywords: c++,documentation,mcp,model-context-protocol,qt4
Classifier: Development Status :: 4 - Beta
Classifier: Intended Audience :: Developers
Classifier: License :: OSI Approved :: MIT License
Classifier: Programming Language :: Python :: 3
Classifier: Programming Language :: Python :: 3.11
Classifier: Programming Language :: Python :: 3.12
Classifier: Programming Language :: Python :: 3.13
Classifier: Topic :: Office/Business :: Groupware
Classifier: Topic :: Software Development :: Libraries :: Python Modules
Requires-Python: >=3.11
Requires-Dist: beautifulsoup4>=4.12.0
Requires-Dist: lxml>=4.9.0
Requires-Dist: markdownify>=0.11.0
Requires-Dist: mcp[cli]>=1.14.1
Requires-Dist: python-dotenv>=1.0
Requires-Dist: uvicorn>=0.30
Provides-Extra: dev
Requires-Dist: pytest; extra == 'dev'
Requires-Dist: ruff; extra == 'dev'
